secret_rotator/__init__.py
secret_rotator/backup_manager.py
secret_rotator/cli.py
secret_rotator/encryption_manager.py
secret_rotator/key_backup_manager.py
secret_rotator/main.py
secret_rotator/plugin_system.py
secret_rotator/py.typed
secret_rotator/rotation_engine.py
secret_rotator/scheduler.py
secret_rotator/secret_access.py
secret_rotator/setup_wizard.py
secret_rotator/version.py
secret_rotator/web_interface.py
secret_rotator/config/__init__.py
secret_rotator/config/settings.py
secret_rotator/providers/__init__.py
secret_rotator/providers/base.py
secret_rotator/providers/file_provider.py
secret_rotator/providers/file_provider0.py
secret_rotator/rotators/__init__.py
secret_rotator/rotators/advanced_rotators.py
secret_rotator/rotators/base.py
secret_rotator/rotators/password_rotator.py
secret_rotator/tools/__init__.py
secret_rotator/tools/manage_key_backups.py
secret_rotator/utils/__init__.py
secret_rotator/utils/logger.py
secret_rotator/utils/retry.py
secret_rotator-1.2.0.dist-info/licenses/LICENSE.md
secret_rotator-1.2.0.dist-info/METADATA
secret_rotator-1.2.0.dist-info/WHEEL
secret_rotator-1.2.0.dist-info/entry_points.txt
secret_rotator-1.2.0.dist-info/top_level.txt
secret_rotator-1.2.0.dist-info/RECORD
