Metadata-Version: 2.4
Name: secret-rotator
Version: 1.2.0
Summary: Automated secret rotation system with encryption and backup management
Author-email: othaimeen <othaimeen.dev@gmail.com>
License: MIT
Project-URL: Homepage, https://github.com/othaime-en/secret-rotator
Project-URL: Documentation, https://github.com/othaime-en/secret-rotator#readme
Project-URL: Repository, https://github.com/othaime-en/secret-rotator
Project-URL: Issues, https://github.com/othaime-en/secret-rotator/issues
Project-URL: Changelog, https://github.com/othaime-en/secret-rotator/blob/main/CHANGELOG.md
Keywords: security,secrets,rotation,encryption,automation
Classifier: Development Status :: 4 - Beta
Classifier: Intended Audience :: Developers
Classifier: Intended Audience :: System Administrators
Classifier: License :: OSI Approved :: MIT License
Classifier: Operating System :: OS Independent
Classifier: Programming Language :: Python :: 3
Classifier: Programming Language :: Python :: 3.9
Classifier: Programming Language :: Python :: 3.10
Classifier: Programming Language :: Python :: 3.11
Classifier: Programming Language :: Python :: 3.12
Classifier: Topic :: Security
Classifier: Topic :: System :: Systems Administration
Requires-Python: >=3.9
License-File: LICENSE.md
Requires-Dist: cryptography>=46.0.0
Requires-Dist: PyYAML>=6.0.0
Requires-Dist: schedule>=1.2.0
Provides-Extra: dev
Requires-Dist: pytest>=7.0.0; extra == "dev"
Requires-Dist: pytest-cov>=4.0.0; extra == "dev"
Requires-Dist: black>=23.0.0; extra == "dev"
Requires-Dist: flake8>=6.0.0; extra == "dev"
Requires-Dist: mypy>=1.0.0; extra == "dev"
Requires-Dist: build>=1.0.0; extra == "dev"
Requires-Dist: twine>=4.0.0; extra == "dev"
Provides-Extra: databases
Requires-Dist: psycopg2-binary>=2.9.0; extra == "databases"
Requires-Dist: pymongo>=4.15.0; extra == "databases"
Requires-Dist: mysql-connector-python>=8.0.0; extra == "databases"
Provides-Extra: advanced
Requires-Dist: PyJWT>=2.10.0; extra == "advanced"
Requires-Dist: pyshamir>=1.0.4; extra == "advanced"
Requires-Dist: Requests>=2.32.0; extra == "advanced"
Provides-Extra: all
Requires-Dist: secret-rotator[advanced,databases,dev]; extra == "all"
Dynamic: license-file
